zdppy_cache/__init__.py
zdppy_cache/cache.py
zdppy_cache/core.py
zdppy_cache/fanout.py
zdppy_cache/persistent.py
zdppy_cache/recipes.py
zdppy_cache/user_cache.py
zdppy_cache/utils.py
zdppy_cache/zdppy_api.py
zdppy_cache-0.1.2.dist-info/LICENSE
zdppy_cache-0.1.2.dist-info/METADATA
zdppy_cache-0.1.2.dist-info/WHEEL
zdppy_cache-0.1.2.dist-info/RECORD
