Metadata-Version: 2.1
Name: zdppy-cache
Version: 0.1.2
Summary: Python轻量级低代码缓存框架
Author: zhangdapeng520
Author-email: 1156956636@qq.com
Requires-Python: >=3.8,<4.0
Classifier: Programming Language :: Python :: 3
Classifier: Programming Language :: Python :: 3.8
Classifier: Programming Language :: Python :: 3.9
Classifier: Programming Language :: Python :: 3.10
Classifier: Programming Language :: Python :: 3.11
Classifier: Programming Language :: Python :: 3.12
